{
	"configurations" : 
	[
		{
			"directories" : 
			[
				{
					"build" : ".",
					"childIndexes" : 
					[
						1
					],
					"jsonFile" : "directory-.-Debug-f5ebdc15457944623624.json",
					"minimumCMakeVersion" : 
					{
						"string" : "3.16"
					},
					"projectIndex" : 0,
					"source" : ".",
					"targetIndexes" : 
					[
						3
					]
				},
				{
					"build" : "vendored/SDL",
					"jsonFile" : "directory-vendored.SDL-Debug-3493257b83e529c43a77.json",
					"minimumCMakeVersion" : 
					{
						"string" : "3.16"
					},
					"parentIndex" : 0,
					"projectIndex" : 1,
					"source" : "vendored/SDL",
					"targetIndexes" : 
					[
						0,
						1,
						2
					]
				}
			],
			"name" : "Debug",
			"projects" : 
			[
				{
					"childIndexes" : 
					[
						1
					],
					"directoryIndexes" : 
					[
						0
					],
					"name" : "hello",
					"targetIndexes" : 
					[
						3
					]
				},
				{
					"directoryIndexes" : 
					[
						1
					],
					"name" : "SDL3",
					"parentIndex" : 0,
					"targetIndexes" : 
					[
						0,
						1,
						2
					]
				}
			],
			"targets" : 
			[
				{
					"directoryIndex" : 1,
					"id" : "SDL3-shared::@8fb704815aaca498baa2",
					"jsonFile" : "target-SDL3-shared-Debug-53a048566a77cb45f377.json",
					"name" : "SDL3-shared",
					"projectIndex" : 1
				},
				{
					"directoryIndex" : 1,
					"id" : "SDL3_test::@8fb704815aaca498baa2",
					"jsonFile" : "target-SDL3_test-Debug-62f9cc8f34b7ff7f1d48.json",
					"name" : "SDL3_test",
					"projectIndex" : 1
				},
				{
					"directoryIndex" : 1,
					"id" : "SDL_uclibc::@8fb704815aaca498baa2",
					"jsonFile" : "target-SDL_uclibc-Debug-d7502ab524c0e670108f.json",
					"name" : "SDL_uclibc",
					"projectIndex" : 1
				},
				{
					"directoryIndex" : 0,
					"id" : "hello::@6890427a1f51a3e7e1df",
					"jsonFile" : "target-hello-Debug-7b3ec4bc4d9dd2e6d7c5.json",
					"name" : "hello",
					"projectIndex" : 0
				}
			]
		}
	],
	"kind" : "codemodel",
	"paths" : 
	{
		"build" : "/home/rigoc/repos/tmc-SDL3/build",
		"source" : "/home/rigoc/repos/tmc-SDL3"
	},
	"version" : 
	{
		"major" : 2,
		"minor" : 6
	}
}
